LICENSE
MANIFEST.in
README
setup.cfg
setup.py
pyranda/__init__.py
pyranda/__main__.py
pyranda/app.py
pyranda/datum.py
pyranda/jmeno.py
pyranda/jmenos.py
pyranda/kalendar.py
pyranda/kalendar_data_2017.py
pyranda/kraj.py
pyranda/krajs.py
pyranda/mesic.py
pyranda/mesto.py
pyranda/okres.py
pyranda/okress.py
pyranda/osoba.py
pyranda/prijmeni.py
pyranda/prijmenis.py
pyranda/rodnecislo.py
pyranda/zeme.py
pyranda.egg-info/PKG-INFO
pyranda.egg-info/SOURCES.txt
pyranda.egg-info/dependency_links.txt
pyranda.egg-info/entry_points.txt
pyranda.egg-info/not-zip-safe
pyranda.egg-info/top_level.txt
pyranda/demo/__init__.py
pyranda/demo/demo.py