Metadata-Version: 1.1
Name: pyranda
Version: 0.0.23
Summary: Generate random data of common czech names
Home-page: https://github.com/rludva/pyranda
Author: Radomír Ludva
Author-email: rludva@radmi.cz
License: Public Domain
Platform: UNKNOWN
Classifier: Intended Audience :: Developers
Classifier: License :: Public Domain
Classifier: Natural Language :: Czech
Classifier: Operating System :: POSIX :: Linux
Classifier: Programming Language :: Python
Classifier: Programming Language :: Python :: 3
Classifier: Programming Language :: Python :: 3.5
Classifier: Topic :: Software Development :: Libraries
